pyeyes/__init__.py
pyeyes/app.py
pyeyes/config.py
pyeyes/enums.py
pyeyes/error.py
pyeyes/metrics.py
pyeyes/profilers.py
pyeyes/roi.py
pyeyes/slicers.py
pyeyes/themes.py
pyeyes/utils.py
pyeyes/viewers.py
pyeyes/cmap/cmap.py
pyeyes/cmap/lipari.csv
pyeyes/cmap/navia.csv
pyeyes/mpl/dti.py
pyeyes/mpl/mpl_config.py
pyeyes-0.2.0.dist-info/METADATA
pyeyes-0.2.0.dist-info/WHEEL
pyeyes-0.2.0.dist-info/top_level.txt
pyeyes-0.2.0.dist-info/RECORD
