Metadata-Version: 2.2
Name: pyeyes
Version: 0.2.0
Summary: A GUI viewer for high-dimensional image visualization in Python
Author-email: Zachary Shah <zshah9@stanford.edu>, Yonatan Urman <yurman@stanford.edu>
License: MIT
Project-URL: Homepage, https://github.com/zachary-shah/pyeyes
Project-URL: Repository, https://github.com/zachary-shah/pyeyes
Project-URL: Bug Tracker, https://github.com/zachary-shah/pyeyes/issues
Classifier: Programming Language :: Python :: 3
Classifier: License :: OSI Approved :: MIT License
Classifier: Operating System :: OS Independent
Requires-Python: >=3.10
Requires-Dist: numpy>=1.23
Requires-Dist: matplotlib
Requires-Dist: holoviews>=1.20.0
Requires-Dist: bokeh>=3.6.2
Requires-Dist: nibabel
Requires-Dist: scipy
Requires-Dist: jupyter_bokeh
Requires-Dist: scikit-image
Provides-Extra: dev
Requires-Dist: pre-commit; extra == "dev"
Requires-Dist: black; extra == "dev"
